postling/__init__.py
postling/__main__.py
postling/app.py
postling/highlight_url.py
postling/locations.py
postling/postling.scss
postling-0.1.0a1.dist-info/METADATA
postling-0.1.0a1.dist-info/WHEEL
postling-0.1.0a1.dist-info/entry_points.txt
postling-0.1.0a1.dist-info/RECORD
