Metadata-Version: 2.3
Name: postling
Version: 0.1.0a1
Summary: Add your description here
Author-email: Darren Burns <darrenb900@gmail.com>
Requires-Python: >=3.11
Requires-Dist: click-default-group>=1.2.4
Requires-Dist: click>=8.1.7
Requires-Dist: httpx>=0.27.0
Requires-Dist: textual[syntax]>=0.63.4
Requires-Dist: xdg-base-dirs>=6.0.1
